vod_downloader/__init__.py
vod_downloader/vod_downloader.py
wubby_vod_downloader-1.3.0.dist-info/LICENSE
wubby_vod_downloader-1.3.0.dist-info/METADATA
wubby_vod_downloader-1.3.0.dist-info/WHEEL
wubby_vod_downloader-1.3.0.dist-info/entry_points.txt
wubby_vod_downloader-1.3.0.dist-info/top_level.txt
wubby_vod_downloader-1.3.0.dist-info/RECORD
